bhaskara/__init__.py
bhaskara/eq_bhaskara.py
bhaskara/eq_segundo_grau.py
trab_devops_ci_cd_process-0.0.6.dist-info/LICENSE
trab_devops_ci_cd_process-0.0.6.dist-info/METADATA
trab_devops_ci_cd_process-0.0.6.dist-info/WHEEL
trab_devops_ci_cd_process-0.0.6.dist-info/top_level.txt
trab_devops_ci_cd_process-0.0.6.dist-info/RECORD
